odoo/addons/shopinvader_notification_default/README.rst
odoo/addons/shopinvader_notification_default/__init__.py
odoo/addons/shopinvader_notification_default/__manifest__.py
odoo/addons/shopinvader_notification_default/data/email_template.xml
odoo/addons/shopinvader_notification_default/data/shopinvader_notification.xml
odoo/addons/shopinvader_notification_default/i18n/shopinvader_notification_default.pot
odoo/addons/shopinvader_notification_default/readme/CONTRIBUTORS.rst
odoo/addons/shopinvader_notification_default/readme/CREDITS.rst
odoo/addons/shopinvader_notification_default/readme/DESCRIPTION.rst
odoo/addons/shopinvader_notification_default/static/description/index.html
odoo/addons/shopinvader_notification_default/templates/cart_email.xml
odoo/addons/shopinvader_notification_default/templates/customer_address_email.xml
odoo/addons/shopinvader_notification_default/templates/customer_profile_email.xml
odoo/addons/shopinvader_notification_default/templates/invoice_email.xml
odoo/addons/shopinvader_notification_default/templates/layout.xml
odoo/addons/shopinvader_notification_default/templates/sale_email.xml
odoo13_addon_shopinvader_notification_default-13.0.1.0.1.dev3.dist-info/METADATA
odoo13_addon_shopinvader_notification_default-13.0.1.0.1.dev3.dist-info/WHEEL
odoo13_addon_shopinvader_notification_default-13.0.1.0.1.dev3.dist-info/top_level.txt
odoo13_addon_shopinvader_notification_default-13.0.1.0.1.dev3.dist-info/RECORD
