Metadata-Version: 2.1
Name: odoo13-addon-shopinvader_notification_default
Version: 13.0.1.0.1.dev3
Summary: Provide default notification templates for Shopinvader suite.
Home-page: https://github.com/shopinvader/odoo-shopinvader
Author: Camptocamp,Odoo Community Association (OCA)
Author-email: support@odoo-community.org
License: AGPL-3
Classifier: Programming Language :: Python
Classifier: Framework :: Odoo
Classifier: Framework :: Odoo :: 13.0
Classifier: License :: OSI Approved :: GNU Affero General Public License v3
Requires-Python: >=3.5
Requires-Dist: odoo13-addon-email-template-qweb
Requires-Dist: odoo13-addon-shopinvader
Requires-Dist: odoo <13.1dev,>=13.0a
